coreason_maco/__init__.py
coreason_maco/client.py
coreason_maco/core/__init__.py
coreason_maco/core/controller.py
coreason_maco/core/interfaces.py
coreason_maco/core/manifest.py
coreason_maco/engine/__init__.py
coreason_maco/engine/handlers.py
coreason_maco/engine/resolver.py
coreason_maco/engine/runner.py
coreason_maco/engine/topology.py
coreason_maco/events/__init__.py
coreason_maco/events/protocol.py
coreason_maco/infrastructure/__init__.py
coreason_maco/infrastructure/server_defaults.py
coreason_maco/main.py
coreason_maco/server.py
coreason_maco/strategies/__init__.py
coreason_maco/strategies/council.py
coreason_maco/utils/__init__.py
coreason_maco/utils/context.py
coreason_maco/utils/logger.py
coreason_maco-0.4.0.dist-info/METADATA
coreason_maco-0.4.0.dist-info/WHEEL
coreason_maco-0.4.0.dist-info/licenses/LICENSE
coreason_maco-0.4.0.dist-info/licenses/NOTICE
coreason_maco-0.4.0.dist-info/RECORD
