Metadata-Version: 2.4
Name: coreason_maco
Version: 0.4.0
Summary: Coreason MACO: A Multi-Agent Collaborative Orchestrator for robust strategic reasoning and graph-based execution.
License: # The Prosperity Public License 3.0.0
License-File: LICENSE
License-File: NOTICE
Author: Gowtham A Rao
Author-email: gowtham.rao@coreason.ai
Requires-Python: >=3.12, <3.15
Classifier: License :: Other/Proprietary License
Classifier: Programming Language :: Python :: 3.12
Classifier: Operating System :: OS Independent
Requires-Dist: aiofiles (>=23.0.0)
Requires-Dist: anyio (>=4.12.1,<5.0.0)
Requires-Dist: coreason-identity (>=0.4.1,<0.5.0)
Requires-Dist: coreason-manifest (>=0.6.0,<0.7.0)
Requires-Dist: fastapi (>=0.128.0,<0.129.0)
Requires-Dist: httpx (>=0.28.1,<0.29.0)
Requires-Dist: jinja2 (>=3.1.6,<4.0.0)
Requires-Dist: loguru (>=0.7.2,<0.8.0)
Requires-Dist: networkx
Requires-Dist: pydantic (>=2.0,<3.0)
Requires-Dist: types-aiofiles (>=23.0.0)
Requires-Dist: uvicorn (>=0.40.0,<0.41.0)
Project-URL: Documentation, https://github.com/CoReason-AI/coreason_maco
Project-URL: Homepage, https://github.com/CoReason-AI/coreason_maco
Project-URL: Repository, https://github.com/CoReason-AI/coreason_maco
